{"login":"eliperelman","id":285899,"avatar_url":"https://avatars.githubusercontent.com/u/285899?v=3","gravatar_id":"","url":"https://api.github.com/users/eliperelman","html_url":"https://github.com/eliperelman","followers_url":"https://api.github.com/users/eliperelman/followers","following_url":"https://api.github.com/users/eliperelman/following{/other_user}","gists_url":"https://api.github.com/users/eliperelman/gists{/gist_id}","starred_url":"https://api.github.com/users/eliperelman/starred{/owner}{/repo}","subscriptions_url":"https://api.github.com/users/eliperelman/subscriptions","organizations_url":"https://api.github.com/users/eliperelman/orgs","repos_url":"https://api.github.com/users/eliperelman/repos","events_url":"https://api.github.com/users/eliperelman/events{/privacy}","received_events_url":"https://api.github.com/users/eliperelman/received_events","type":"User","site_admin":false,"name":"Eli Perelman","company":"Mozilla","blog":"http://eliperelman.com","location":"Persia, IA","email":"eli@eliperelman.com","hireable":null,"bio":null,"public_repos":77,"public_gists":43,"followers":57,"following":8,"created_at":"2010-05-24T18:37:26Z","updated_at":"2015-10-15T17:27:10Z"}